fashion_mnist_classifier-0.1.11.dist-info/licenses/LICENSE
my_project/__init__.py
my_project/app.py
my_project/config.py
my_project/dataset.py
my_project/model.py
my_project/plots.py
my_project/train.py
my_project/train_exp1.py
fashion_mnist_classifier-0.1.11.dist-info/METADATA
fashion_mnist_classifier-0.1.11.dist-info/WHEEL
fashion_mnist_classifier-0.1.11.dist-info/entry_points.txt
fashion_mnist_classifier-0.1.11.dist-info/top_level.txt
fashion_mnist_classifier-0.1.11.dist-info/RECORD
